SlitheringFm.py
setup.py
SlitheringFM.egg-info/PKG-INFO
SlitheringFM.egg-info/SOURCES.txt
SlitheringFM.egg-info/dependency_links.txt
SlitheringFM.egg-info/top_level.txt