Metadata-Version: 1.0
Name: SlitheringFM
Version: 0.2
Summary: A fork of a think wrapper for accessing the LastFM API
Home-page: https://github.com/malcolm2608/lastfmapi
Author: Malcom Clark
Author-email: malcolmclark2608@gmail.com
License: http://www.opensource.org/licenses/mit-license.php
Keywords: lastFM API python3 python
Platform: UNKNOWN
